setup.py
lgbtq/__init__.py
lgbtq.egg-info/PKG-INFO
lgbtq.egg-info/SOURCES.txt
lgbtq.egg-info/dependency_links.txt
lgbtq.egg-info/top_level.txt