Metadata-Version: 1.0
Name: lgbtq
Version: 1.1.2
Summary: LGBTQ+ Expander
Home-page: UNKNOWN
Author: UNKNOWN
Author-email: UNKNOWN
License: UNKNOWN
Platform: UNKNOWN
